{
	"name": "androcula",
	"$schema": "vscode://schemas/color-theme",
	"type": "dark",
	"colors": {
		"activityBar.background": "#23262e",
		"activityBar.foreground": "#baafc0",
		"activityBarBadge.background": "#00b0ff",
		"activityBarBadge.foreground": "#20232b",
		"badge.background": "#00b0ff",
		"badge.foreground": "#20232b",
		"button.background": "#00e8c5cc",
		"button.hoverBackground": "#07d4b6cc",
		"debugExceptionWidget.background": "#ff9f2e60",
		"debugExceptionWidget.border": "#ff9f2e60",
		"debugToolBar.background": "#20232a",
		"diffEditor.insertedTextBackground": "#29bf1220",
		"diffEditor.removedTextBackground": "#f21b3f20",
		"dropdown.background": "#2b303b",
		"dropdown.border": "#363c49",
		"editor.background": "#23262e",
		"editor.findMatchBackground": "#f39d12d7",
		"editor.findMatchHighlightBackground": "#59b8b377",
		"editor.foreground": "#d5ced9",
		"editor.hoverHighlightBackground": "#373941",
		"editor.lineHighlightBackground": "#2e323d",
		"editor.lineHighlightBorder": "#2e323d",
		"editor.rangeHighlightBackground": "#372f3c",
		"editor.selectionBackground": "#3d4352",
		"editor.selectionHighlightBackground": "#4f435580",
		"editor.wordHighlightBackground": "#4f4355",
		"editor.wordHighlightStrongBackground": "#db45a280",
		"editorBracketMatch.background": "#746f77",
		"editorBracketMatch.border": "#746f77",
		"editorCodeLens.foreground": "#746f77",
		"editorCursor.foreground": "#ffffff",
		"editorError.foreground": "#fc644d",
		"editorGroup.dropBackground": "#495061d7",
		"editorGroupHeader.tabsBackground": "#23262e",
		"editorGutter.addedBackground": "#9bc53dbb",
		"editorGutter.deletedBackground": "#fc644dbb",
		"editorGutter.modifiedBackground": "#5bc0ebbb",
		"editorHoverWidget.background": "#373941",
		"editorHoverWidget.border": "#00e8c5cc",
		"editorIndentGuide.activeBackground": "#585c66",
		"editorIndentGuide.background": "#333844",
		"editorLineNumber.foreground": "#746f77",
		"editorLink.activeForeground": "#3b79c7",
		"editorOverviewRuler.border": "#1b1d23",
		"editorRuler.foreground": "#4f4355",
		"editorSuggestWidget.background": "#20232a",
		"editorSuggestWidget.border": "#372f3c",
		"editorSuggestWidget.selectedBackground": "#373941",
		"editorWarning.foreground": "#ff9f2e",
		"editorWhitespace.foreground": "#333844",
		"editorWidget.background": "#20232a",
		"errorForeground": "#fc644d",
		"extensionButton.prominentBackground": "#07d4b6cc",
		"extensionButton.prominentHoverBackground": "#07d4b5b0",
		"focusBorder": "#746f77",
		"foreground": "#d5ced9",
		"input.background": "#2b303b",
		"input.placeholderForeground": "#746f77",
		"inputOption.activeBorder": "#c668ba",
		"inputValidation.errorBackground": "#d65343",
		"inputValidation.errorBorder": "#d65343",
		"inputValidation.infoBackground": "#3a6395",
		"inputValidation.infoBorder": "#3a6395",
		"inputValidation.warningBackground": "#de9237",
		"inputValidation.warningBorder": "#de9237",
		"list.activeSelectionBackground": "#23262e",
		"list.activeSelectionForeground": "#00e8c6",
		"list.dropBackground": "#3a404e",
		"list.focusBackground": "#282b35",
		"list.focusForeground": "#eeeeee",
		"list.hoverBackground": "#23262e",
		"list.hoverForeground": "#eeeeee",
		"list.inactiveSelectionBackground": "#23262e",
		"list.inactiveSelectionForeground": "#00e8c6",
		"merge.currentContentBackground": "#f9267240",
		"merge.currentHeaderBackground": "#f92672",
		"merge.incomingContentBackground": "#3b79c740",
		"merge.incomingHeaderBackground": "#3b79c7bb",
		"panel.background": "#23262e",
		"panel.border": "#1b1d23",
		"panelTitle.activeBorder": "#23262e",
		"panelTitle.inactiveForeground": "#746f77",
		"peekView.border": "#23262e",
		"peekViewEditor.background": "#1a1c22",
		"peekViewEditor.matchHighlightBackground": "#ff9f2e60",
		"peekViewResult.background": "#1a1c22",
		"peekViewResult.matchHighlightBackground": "#ff9f2e60",
		"peekViewResult.selectionBackground": "#23262e",
		"peekViewTitle.background": "#1a1c22",
		"peekViewTitleDescription.foreground": "#746f77",
		"pickerGroup.border": "#4f4355",
		"pickerGroup.foreground": "#746f77",
		"progressBar.background": "#c668ba",
		"scrollbar.shadow": "#23262e",
		"scrollbarSlider.activeBackground": "#3a3f4ccc",
		"scrollbarSlider.background": "#3a3f4c77",
		"scrollbarSlider.hoverBackground": "#3a3f4caa",
		"selection.background": "#746f77",
		"sideBar.background": "#23262e",
		"sideBar.foreground": "#746f77",
		"sideBarSectionHeader.background": "#23262e",
		"sideBarTitle.foreground": "#00e8c6",
		"statusBar.background": "#23262e",
		"statusBar.debuggingBackground": "#fc644d",
		"statusBar.noFolderBackground": "#23262e",
		"statusBarItem.activeBackground": "#00e8c5cc",
		"statusBarItem.hoverBackground": "#07d4b5b0",
		"statusBarItem.prominentBackground": "#07d4b5b0",
		"statusBarItem.prominentHoverBackground": "#00e8c5cc",
		"tab.activeBackground": "#23262e",
		"tab.activeForeground": "#00e8c6",
		"tab.inactiveBackground": "#23262e",
		"tab.inactiveForeground": "#746f77",
		"terminal.ansiBlue": "#7cb7ff",
		"terminal.ansiBrightBlue": "#7cb7ff",
		"terminal.ansiBrightCyan": "#00e8c6",
		"terminal.ansiBrightGreen": "#96e072",
		"terminal.ansiBrightMagenta": "#ff00aa",
		"terminal.ansiBrightRed": "#ee5d43",
		"terminal.ansiBrightYellow": "#ffe66d",
		"terminal.ansiCyan": "#00e8c6",
		"terminal.ansiGreen": "#96e072",
		"terminal.ansiMagenta": "#ff00aa",
		"terminal.ansiRed": "#ee5d43",
		"terminal.ansiYellow": "#ffe66d",
		"terminalCursor.background": "#23262e",
		"terminalCursor.foreground": "#ffe66d",
		"titleBar.activeBackground": "#23262e",
		"walkThrough.embeddedEditorBackground": "#23262e",
		"widget.shadow": "#14151a",
		//"activityBar.activeBorder": "#baafc0",
		//"activityBar.dropBorder": "#baafc0",
		//"activityBar.inactiveForeground": "#baafc066",
		//"banner.background": "#23262e",
		//"banner.foreground": "#00e8c6",
		//"banner.iconForeground": "#3794ff",
		//"breadcrumb.activeSelectionForeground": "#e9e6eb",
		//"breadcrumb.background": "#23262e",
		//"breadcrumb.focusForeground": "#e9e6eb",
		//"breadcrumb.foreground": "#d5ced9cc",
		//"breadcrumbPicker.background": "#20232a",
		//"button.foreground": "#ffffff",
		//"button.secondaryBackground": "#3a3d41",
		//"button.secondaryForeground": "#ffffff",
		//"button.secondaryHoverBackground": "#45494e",
		//"button.separator": "#ffffff66",
		//"charts.blue": "#3794ff",
		//"charts.foreground": "#d5ced9",
		//"charts.green": "#89d185",
		//"charts.lines": "#d5ced980",
		//"charts.orange": "#d18616",
		//"charts.purple": "#b180d7",
		//"charts.red": "#fc644d",
		//"charts.yellow": "#ff9f2e",
		//"checkbox.background": "#2b303b",
		//"checkbox.border": "#363c49",
		//"checkbox.foreground": "#f0f0f0",
		//"commandCenter.activeBackground": "#5a5d5e50",
		//"commandCenter.activeForeground": "#cccccc",
		//"commandCenter.border": "#1b1d23",
		//"commandCenter.foreground": "#cccccc",
		//"debugConsole.errorForeground": "#fc644d",
		//"debugConsole.infoForeground": "#3794ff",
		//"debugConsole.sourceForeground": "#d5ced9",
		//"debugConsole.warningForeground": "#ff9f2e",
		//"debugConsoleInputIcon.foreground": "#d5ced9",
		//"debugIcon.breakpointCurrentStackframeForeground": "#ffcc00",
		//"debugIcon.breakpointDisabledForeground": "#848484",
		//"debugIcon.breakpointForeground": "#e51400",
		//"debugIcon.breakpointStackframeForeground": "#89d185",
		//"debugIcon.breakpointUnverifiedForeground": "#848484",
		//"debugIcon.continueForeground": "#75beff",
		//"debugIcon.disconnectForeground": "#f48771",
		//"debugIcon.pauseForeground": "#75beff",
		//"debugIcon.restartForeground": "#89d185",
		//"debugIcon.startForeground": "#89d185",
		//"debugIcon.stepBackForeground": "#75beff",
		//"debugIcon.stepIntoForeground": "#75beff",
		//"debugIcon.stepOutForeground": "#75beff",
		//"debugIcon.stepOverForeground": "#75beff",
		//"debugIcon.stopForeground": "#f48771",
		//"debugTokenExpression.boolean": "#4e94ce",
		//"debugTokenExpression.error": "#f48771",
		//"debugTokenExpression.name": "#c586c0",
		//"debugTokenExpression.number": "#b5cea8",
		//"debugTokenExpression.string": "#ce9178",
		//"debugTokenExpression.value": "#cccccc99",
		//"debugView.exceptionLabelBackground": "#6c2022",
		//"debugView.exceptionLabelForeground": "#d5ced9",
		//"debugView.stateLabelBackground": "#88888844",
		//"debugView.stateLabelForeground": "#d5ced9",
		//"debugView.valueChangedHighlight": "#569cd6",
		//"descriptionForeground": "#d5ced9b3",
		//"diffEditor.diagonalFill": "#cccccc33",
		//"diffEditor.insertedLineBackground": "#9bb95533",
		//"diffEditor.removedLineBackground": "#ff000033",
		//"disabledForeground": "#cccccc80",
		//"dropdown.foreground": "#f0f0f0",
		//"editor.findRangeHighlightBackground": "#3a3d4166",
		//"editor.focusedStackFrameHighlightBackground": "#7abd7a4d",
		//"editor.foldBackground": "#3d43524d",
		//"editor.inactiveSelectionBackground": "#3d435280",
		//"editor.inlineValuesBackground": "#ffc80033",
		//"editor.inlineValuesForeground": "#ffffff80",
		//"editor.linkedEditingBackground": "#ff00004d",
		//"editor.snippetFinalTabstopHighlightBorder": "#525252",
		//"editor.snippetTabstopHighlightBackground": "#7c7c7c4d",
		//"editor.stackFrameHighlightBackground": "#ffff0033",
		//"editor.symbolHighlightBackground": "#59b8b377",
		//"editorActiveLineNumber.foreground": "#c6c6c6",
		//"editorBracketHighlight.foreground1": "#ffd700",
		//"editorBracketHighlight.foreground2": "#da70d6",
		//"editorBracketHighlight.foreground3": "#179fff",
		//"editorBracketHighlight.foreground4": "#00000000",
		//"editorBracketHighlight.foreground5": "#00000000",
		//"editorBracketHighlight.foreground6": "#00000000",
		//"editorBracketHighlight.unexpectedBracket.foreground": "#ff1212cc",
		//"editorBracketPairGuide.activeBackground1": "#00000000",
		//"editorBracketPairGuide.activeBackground2": "#00000000",
		//"editorBracketPairGuide.activeBackground3": "#00000000",
		//"editorBracketPairGuide.activeBackground4": "#00000000",
		//"editorBracketPairGuide.activeBackground5": "#00000000",
		//"editorBracketPairGuide.activeBackground6": "#00000000",
		//"editorBracketPairGuide.background1": "#00000000",
		//"editorBracketPairGuide.background2": "#00000000",
		//"editorBracketPairGuide.background3": "#00000000",
		//"editorBracketPairGuide.background4": "#00000000",
		//"editorBracketPairGuide.background5": "#00000000",
		//"editorBracketPairGuide.background6": "#00000000",
		//"editorCommentsWidget.rangeActiveBackground": "#23262e1a",
		//"editorCommentsWidget.rangeActiveBorder": "#23262e66",
		//"editorCommentsWidget.rangeBackground": "#23262e1a",
		//"editorCommentsWidget.rangeBorder": "#23262e66",
		//"editorCommentsWidget.resolvedBorder": "#cccccc80",
		//"editorCommentsWidget.unresolvedBorder": "#23262e",
		//"editorGhostText.foreground": "#ffffff56",
		//"editorGroup.border": "#444444",
		//"editorGroup.dropIntoPromptBackground": "#20232a",
		//"editorGroup.dropIntoPromptForeground": "#d5ced9",
		//"editorGroupHeader.noTabsBackground": "#23262e",
		//"editorGutter.background": "#23262e",
		//"editorGutter.commentRangeForeground": "#23262e",
		//"editorGutter.foldingControlForeground": "#c5c5c5",
		//"editorHint.foreground": "#eeeeeeb3",
		//"editorHoverWidget.foreground": "#d5ced9",
		//"editorHoverWidget.highlightForeground": "#2aaaff",
		//"editorHoverWidget.statusBarBackground": "#42444e",
		//"editorInfo.foreground": "#3794ff",
		//"editorInlayHint.background": "#00b0ff99",
		//"editorInlayHint.foreground": "#20232bcc",
		//"editorInlayHint.parameterBackground": "#00b0ff99",
		//"editorInlayHint.parameterForeground": "#20232bcc",
		//"editorInlayHint.typeBackground": "#00b0ff99",
		//"editorInlayHint.typeForeground": "#20232bcc",
		//"editorLightBulb.foreground": "#ffcc00",
		//"editorLightBulbAutoFix.foreground": "#75beff",
		//"editorLineNumber.activeForeground": "#c6c6c6",
		//"editorMarkerNavigation.background": "#23262e",
		//"editorMarkerNavigationError.background": "#fc644d",
		//"editorMarkerNavigationError.headerBackground": "#fc644d1a",
		//"editorMarkerNavigationInfo.background": "#3794ff",
		//"editorMarkerNavigationInfo.headerBackground": "#3794ff1a",
		//"editorMarkerNavigationWarning.background": "#ff9f2e",
		//"editorMarkerNavigationWarning.headerBackground": "#ff9f2e1a",
		//"editorOverviewRuler.addedForeground": "#9bc53d70",
		//"editorOverviewRuler.bracketMatchForeground": "#a0a0a0",
		//"editorOverviewRuler.commonContentForeground": "#60606066",
		//"editorOverviewRuler.currentContentForeground": "#f92672",
		//"editorOverviewRuler.deletedForeground": "#fc644d70",
		//"editorOverviewRuler.errorForeground": "#ff1212b3",
		//"editorOverviewRuler.findMatchForeground": "#d186167e",
		//"editorOverviewRuler.incomingContentForeground": "#3b79c7bb",
		//"editorOverviewRuler.infoForeground": "#3794ff",
		//"editorOverviewRuler.modifiedForeground": "#5bc0eb70",
		//"editorOverviewRuler.rangeHighlightForeground": "#007acc99",
		//"editorOverviewRuler.selectionHighlightForeground": "#a0a0a0cc",
		//"editorOverviewRuler.warningForeground": "#ff9f2e",
		//"editorOverviewRuler.wordHighlightForeground": "#a0a0a0cc",
		//"editorOverviewRuler.wordHighlightStrongForeground": "#c0a0c0cc",
		//"editorPane.background": "#23262e",
		//"editorStickyScroll.background": "#23262e",
		//"editorStickyScrollHover.background": "#2a2d2e",
		//"editorSuggestWidget.focusHighlightForeground": "#2aaaff",
		//"editorSuggestWidget.foreground": "#d5ced9",
		//"editorSuggestWidget.highlightForeground": "#2aaaff",
		//"editorSuggestWidget.selectedForeground": "#00e8c6",
		//"editorSuggestWidgetStatus.foreground": "#d5ced980",
		//"editorUnicodeHighlight.background": "#bd9b0326",
		//"editorUnicodeHighlight.border": "#bd9b03",
		//"editorUnnecessaryCode.opacity": "#000000aa",
		//"editorWidget.border": "#454545",
		//"editorWidget.foreground": "#d5ced9",
		//"extensionBadge.remoteBackground": "#00b0ff",
		//"extensionBadge.remoteForeground": "#20232b",
		//"extensionButton.prominentForeground": "#ffffff",
		//"extensionIcon.preReleaseForeground": "#1d9271",
		//"extensionIcon.sponsorForeground": "#d758b3",
		//"extensionIcon.starForeground": "#ff8e00",
		//"extensionIcon.verifiedForeground": "#3794ff",
		//"gitDecoration.addedResourceForeground": "#81b88b",
		//"gitDecoration.conflictingResourceForeground": "#e4676b",
		//"gitDecoration.deletedResourceForeground": "#c74e39",
		//"gitDecoration.ignoredResourceForeground": "#8c8c8c",
		//"gitDecoration.modifiedResourceForeground": "#e2c08d",
		//"gitDecoration.renamedResourceForeground": "#73c991",
		//"gitDecoration.stageDeletedResourceForeground": "#c74e39",
		//"gitDecoration.stageModifiedResourceForeground": "#e2c08d",
		//"gitDecoration.submoduleResourceForeground": "#8db9e2",
		//"gitDecoration.untrackedResourceForeground": "#73c991",
		//"icon.foreground": "#c5c5c5",
		//"input.foreground": "#d5ced9",
		//"inputOption.activeBackground": "#746f7766",
		//"inputOption.activeForeground": "#ffffff",
		//"inputOption.hoverBackground": "#5a5d5e80",
		//"interactive.activeCodeBorder": "#23262e",
		//"interactive.inactiveCodeBorder": "#23262e",
		//"issues.closed": "#cb2431",
		//"issues.newIssueDecoration": "#ffffff48",
		//"issues.open": "#22863a",
		//"keybindingLabel.background": "#8080802b",
		//"keybindingLabel.border": "#33333399",
		//"keybindingLabel.bottomBorder": "#44444499",
		//"keybindingLabel.foreground": "#cccccc",
		//"keybindingTable.headerBackground": "#d5ced90a",
		//"keybindingTable.rowsBackground": "#d5ced90a",
		//"list.deemphasizedForeground": "#8c8c8c",
		//"list.errorForeground": "#f88070",
		//"list.filterMatchBackground": "#59b8b377",
		//"list.focusHighlightForeground": "#2aaaff",
		//"list.focusOutline": "#746f77",
		//"list.highlightForeground": "#2aaaff",
		//"list.invalidItemForeground": "#b89500",
		//"list.warningForeground": "#cca700",
		//"listFilterWidget.background": "#20232a",
		//"listFilterWidget.noMatchesOutline": "#be1100",
		//"listFilterWidget.outline": "#00000000",
		//"listFilterWidget.shadow": "#14151a",
		//"menu.background": "#2b303b",
		//"menu.foreground": "#f0f0f0",
		//"menu.selectionBackground": "#23262e",
		//"menu.selectionForeground": "#00e8c6",
		//"menu.separatorBackground": "#606060",
		//"menubar.selectionBackground": "#5a5d5e50",
		//"menubar.selectionForeground": "#cccccc",
		//"merge.commonContentBackground": "#60606029",
		//"merge.commonHeaderBackground": "#60606066",
		//"mergeEditor.change.background": "#9bb95533",
		//"mergeEditor.change.word.background": "#9ccc2c33",
		//"mergeEditor.conflict.handled.minimapOverViewRuler": "#adaca8ee",
		//"mergeEditor.conflict.handledFocused.border": "#c1c1c1cc",
		//"mergeEditor.conflict.handledUnfocused.border": "#86868649",
		//"mergeEditor.conflict.unhandled.minimapOverViewRuler": "#fcba03",
		//"mergeEditor.conflict.unhandledFocused.border": "#ffa600",
		//"mergeEditor.conflict.unhandledUnfocused.border": "#ffa6007a",
		//"mergeEditor.conflictingLines.background": "#ffea0047",
		//"minimap.errorHighlight": "#ff1212b3",
		//"minimap.findMatchHighlight": "#d18616",
		//"minimap.foregroundOpacity": "#000000",
		//"minimap.selectionHighlight": "#264f78",
		//"minimap.selectionOccurrenceHighlight": "#676767",
		//"minimap.warningHighlight": "#ff9f2e",
		//"minimapGutter.addedBackground": "#9bc53dbb",
		//"minimapGutter.deletedBackground": "#fc644dbb",
		//"minimapGutter.modifiedBackground": "#5bc0ebbb",
		//"minimapSlider.activeBackground": "#3a3f4c66",
		//"minimapSlider.background": "#3a3f4c3c",
		//"minimapSlider.hoverBackground": "#3a3f4c55",
		//"notebook.cellBorderColor": "#23262e",
		//"notebook.cellEditorBackground": "#23262e",
		//"notebook.cellInsertionIndicator": "#746f77",
		//"notebook.cellStatusBarItemHoverBackground": "#ffffff26",
		//"notebook.cellToolbarSeparator": "#80808059",
		//"notebook.editorBackground": "#23262e",
		//"notebook.focusedCellBorder": "#746f77",
		//"notebook.focusedEditorBorder": "#746f77",
		//"notebook.inactiveFocusedCellBorder": "#23262e",
		//"notebook.selectedCellBackground": "#23262e",
		//"notebook.selectedCellBorder": "#23262e",
		//"notebook.symbolHighlightBackground": "#ffffff0b",
		//"notebookScrollbarSlider.activeBackground": "#3a3f4ccc",
		//"notebookScrollbarSlider.background": "#3a3f4c77",
		//"notebookScrollbarSlider.hoverBackground": "#3a3f4caa",
		//"notebookStatusErrorIcon.foreground": "#fc644d",
		//"notebookStatusRunningIcon.foreground": "#d5ced9",
		//"notebookStatusSuccessIcon.foreground": "#89d185",
		//"notificationCenterHeader.background": "#2a2e37",
		//"notificationLink.foreground": "#3794ff",
		//"notifications.background": "#20232a",
		//"notifications.border": "#2a2e37",
		//"notifications.foreground": "#d5ced9",
		//"notificationsErrorIcon.foreground": "#fc644d",
		//"notificationsInfoIcon.foreground": "#3794ff",
		//"notificationsWarningIcon.foreground": "#ff9f2e",
		//"panel.dropBorder": "#e7e7e7",
		//"panelSection.border": "#1b1d23",
		//"panelSection.dropBackground": "#495061d7",
		//"panelSectionHeader.background": "#80808033",
		//"panelTitle.activeForeground": "#e7e7e7",
		//"peekViewEditorGutter.background": "#1a1c22",
		//"peekViewResult.fileForeground": "#ffffff",
		//"peekViewResult.lineForeground": "#bbbbbb",
		//"peekViewResult.selectionForeground": "#ffffff",
		//"peekViewTitleLabel.foreground": "#ffffff",
		//"ports.iconRunningProcessForeground": "#00b0ff",
		//"problemsErrorIcon.foreground": "#fc644d",
		//"problemsInfoIcon.foreground": "#3794ff",
		//"problemsWarningIcon.foreground": "#ff9f2e",
		//"pullRequests.notification": "#3794ff",
		//"quickInput.background": "#20232a",
		//"quickInput.foreground": "#d5ced9",
		//"quickInputList.focusBackground": "#23262e",
		//"quickInputList.focusForeground": "#00e8c6",
		//"quickInputTitle.background": "#ffffff1b",
		//"remoteHub.decorations.addedForegroundColor": "#81b88b",
		//"remoteHub.decorations.conflictForegroundColor": "#e4676b",
		//"remoteHub.decorations.deletedForegroundColor": "#c74e39",
		//"remoteHub.decorations.incomingAddedForegroundColor": "#81b88b",
		//"remoteHub.decorations.incomingDeletedForegroundColor": "#c74e39",
		//"remoteHub.decorations.incomingModifiedForegroundColor": "#e2c08d",
		//"remoteHub.decorations.incomingRenamedForegroundColor": "#73c991",
		//"remoteHub.decorations.modifiedForegroundColor": "#e2c08d",
		//"remoteHub.decorations.possibleConflictForegroundColor": "#cca700",
		//"remoteHub.decorations.workspaceRepositoriesView.hasUncommittedChangesForegroundColor": "#e2c08d",
		//"sash.hoverBorder": "#746f77",
		//"scm.providerBorder": "#454545",
		//"searchEditor.findMatchBackground": "#59b8b34f",
		//"settings.checkboxBackground": "#2b303b",
		//"settings.checkboxBorder": "#363c49",
		//"settings.checkboxForeground": "#f0f0f0",
		//"settings.dropdownBackground": "#2b303b",
		//"settings.dropdownBorder": "#363c49",
		//"settings.dropdownForeground": "#f0f0f0",
		//"settings.dropdownListBorder": "#454545",
		//"settings.focusedRowBackground": "#23262e99",
		//"settings.focusedRowBorder": "#ffffff1f",
		//"settings.headerBorder": "#1b1d23",
		//"settings.headerForeground": "#e7e7e7",
		//"settings.modifiedItemIndicator": "#0c7d9d",
		//"settings.numberInputBackground": "#2b303b",
		//"settings.numberInputForeground": "#d5ced9",
		//"settings.rowHoverBackground": "#23262e4d",
		//"settings.sashBorder": "#1b1d23",
		//"settings.textInputBackground": "#2b303b",
		//"settings.textInputForeground": "#d5ced9",
		//"sideBar.dropBackground": "#495061d7",
		//"sideBarSectionHeader.foreground": "#746f77",
		//"sideBySideEditor.horizontalBorder": "#444444",
		//"sideBySideEditor.verticalBorder": "#444444",
		//"statusBar.debuggingForeground": "#ffffff",
		//"statusBar.focusBorder": "#ffffff",
		//"statusBar.foreground": "#ffffff",
		//"statusBar.noFolderForeground": "#ffffff",
		//"statusBarItem.compactHoverBackground": "#ffffff33",
		//"statusBarItem.errorBackground": "#c21d03",
		//"statusBarItem.errorForeground": "#ffffff",
		//"statusBarItem.focusBorder": "#ffffff",
		//"statusBarItem.prominentForeground": "#ffffff",
		//"statusBarItem.remoteBackground": "#00b0ff",
		//"statusBarItem.remoteForeground": "#20232b",
		//"statusBarItem.warningBackground": "#b56000",
		//"statusBarItem.warningForeground": "#ffffff",
		//"symbolIcon.arrayForeground": "#d5ced9",
		//"symbolIcon.booleanForeground": "#d5ced9",
		//"symbolIcon.classForeground": "#ee9d28",
		//"symbolIcon.colorForeground": "#d5ced9",
		//"symbolIcon.constantForeground": "#d5ced9",
		//"symbolIcon.constructorForeground": "#b180d7",
		//"symbolIcon.enumeratorForeground": "#ee9d28",
		//"symbolIcon.enumeratorMemberForeground": "#75beff",
		//"symbolIcon.eventForeground": "#ee9d28",
		//"symbolIcon.fieldForeground": "#75beff",
		//"symbolIcon.fileForeground": "#d5ced9",
		//"symbolIcon.folderForeground": "#d5ced9",
		//"symbolIcon.functionForeground": "#b180d7",
		//"symbolIcon.interfaceForeground": "#75beff",
		//"symbolIcon.keyForeground": "#d5ced9",
		//"symbolIcon.keywordForeground": "#d5ced9",
		//"symbolIcon.methodForeground": "#b180d7",
		//"symbolIcon.moduleForeground": "#d5ced9",
		//"symbolIcon.namespaceForeground": "#d5ced9",
		//"symbolIcon.nullForeground": "#d5ced9",
		//"symbolIcon.numberForeground": "#d5ced9",
		//"symbolIcon.objectForeground": "#d5ced9",
		//"symbolIcon.operatorForeground": "#d5ced9",
		//"symbolIcon.packageForeground": "#d5ced9",
		//"symbolIcon.propertyForeground": "#d5ced9",
		//"symbolIcon.referenceForeground": "#d5ced9",
		//"symbolIcon.snippetForeground": "#d5ced9",
		//"symbolIcon.stringForeground": "#d5ced9",
		//"symbolIcon.structForeground": "#d5ced9",
		//"symbolIcon.textForeground": "#d5ced9",
		//"symbolIcon.typeParameterForeground": "#d5ced9",
		//"symbolIcon.unitForeground": "#d5ced9",
		//"symbolIcon.variableForeground": "#75beff",
		//"tab.activeModifiedBorder": "#3399cc",
		//"tab.border": "#252526",
		//"tab.inactiveModifiedBorder": "#3399cc80",
		//"tab.lastPinnedBorder": "#585858",
		//"tab.unfocusedActiveBackground": "#23262e",
		//"tab.unfocusedActiveForeground": "#00e8c680",
		//"tab.unfocusedActiveModifiedBorder": "#3399cc80",
		//"tab.unfocusedInactiveBackground": "#23262e",
		//"tab.unfocusedInactiveForeground": "#746f7780",
		//"tab.unfocusedInactiveModifiedBorder": "#3399cc40",
		//"terminal.ansiBlack": "#000000",
		//"terminal.ansiBrightBlack": "#666666",
		//"terminal.ansiBrightWhite": "#e5e5e5",
		//"terminal.ansiWhite": "#e5e5e5",
		//"terminal.border": "#1b1d23",
		//"terminal.dropBackground": "#495061d7",
		//"terminal.findMatchBackground": "#f39d12d7",
		//"terminal.findMatchHighlightBackground": "#59b8b377",
		//"terminal.foreground": "#cccccc",
		//"terminal.inactiveSelectionBackground": "#3d435280",
		//"terminal.selectionBackground": "#3d4352",
		//"terminalCommandDecoration.defaultBackground": "#ffffff40",
		//"terminalCommandDecoration.errorBackground": "#f14c4c",
		//"terminalCommandDecoration.successBackground": "#1b81a8",
		//"terminalOverviewRuler.cursorForeground": "#a0a0a0cc",
		//"terminalOverviewRuler.findMatchForeground": "#d186167e",
		//"testing.iconErrored": "#f14c4c",
		//"testing.iconFailed": "#f14c4c",
		//"testing.iconPassed": "#73c991",
		//"testing.iconQueued": "#cca700",
		//"testing.iconSkipped": "#848484",
		//"testing.iconUnset": "#848484",
		//"testing.message.error.decorationForeground": "#fc644d",
		//"testing.message.error.lineBackground": "#ff000033",
		//"testing.message.info.decorationForeground": "#d5ced980",
		//"testing.peekBorder": "#fc644d",
		//"testing.peekHeaderBackground": "#fc644d1a",
		//"testing.runAction": "#73c991",
		//"textBlockQuote.background": "#7f7f7f1a",
		//"textBlockQuote.border": "#007acc80",
		//"textCodeBlock.background": "#0a0a0a66",
		//"textLink.activeForeground": "#3794ff",
		//"textLink.foreground": "#3794ff",
		//"textPreformat.foreground": "#d7ba7d",
		//"textSeparator.foreground": "#ffffff2e",
		//"titleBar.activeForeground": "#cccccc",
		//"titleBar.inactiveBackground": "#23262e99",
		//"titleBar.inactiveForeground": "#cccccc99",
		//"toolbar.activeBackground": "#63666750",
		//"toolbar.hoverBackground": "#5a5d5e50",
		//"tree.indentGuidesStroke": "#585858",
		//"tree.tableColumnsBorder": "#cccccc20",
		//"tree.tableOddRowsBackground": "#d5ced90a",
		//"welcomePage.progress.background": "#2b303b",
		//"welcomePage.progress.foreground": "#3794ff",
		//"welcomePage.tileBackground": "#20232a",
		//"welcomePage.tileHoverBackground": "#262a32",
		//"welcomePage.tileShadow": "#14151a",
		//"activityBar.activeBackground": null,
		//"activityBar.activeFocusBorder": null,
		//"activityBar.border": null,
		//"button.border": null,
		//"commandCenter.background": null,
		//"contrastActiveBorder": null,
		//"contrastBorder": null,
		//"debugToolBar.border": null,
		//"diffEditor.border": null,
		//"diffEditor.insertedTextBorder": null,
		//"diffEditor.removedTextBorder": null,
		//"diffEditorGutter.insertedLineBackground": null,
		//"diffEditorGutter.removedLineBackground": null,
		//"diffEditorOverview.insertedForeground": null,
		//"diffEditorOverview.removedForeground": null,
		//"dropdown.listBackground": null,
		//"editor.findMatchBorder": null,
		//"editor.findMatchHighlightBorder": null,
		//"editor.findRangeHighlightBorder": null,
		//"editor.rangeHighlightBorder": null,
		//"editor.selectionForeground": null,
		//"editor.selectionHighlightBorder": null,
		//"editor.snippetFinalTabstopHighlightBackground": null,
		//"editor.snippetTabstopHighlightBorder": null,
		//"editor.symbolHighlightBorder": null,
		//"editor.wordHighlightBorder": null,
		//"editor.wordHighlightStrongBorder": null,
		//"editorCursor.background": null,
		//"editorError.background": null,
		//"editorError.border": null,
		//"editorGhostText.background": null,
		//"editorGhostText.border": null,
		//"editorGroup.dropIntoPromptBorder": null,
		//"editorGroup.emptyBackground": null,
		//"editorGroup.focusedEmptyBorder": null,
		//"editorGroupHeader.border": null,
		//"editorGroupHeader.tabsBorder": null,
		//"editorHint.border": null,
		//"editorInfo.background": null,
		//"editorInfo.border": null,
		//"editorOverviewRuler.background": null,
		//"editorSuggestWidget.selectedIconForeground": null,
		//"editorUnnecessaryCode.border": null,
		//"editorWarning.background": null,
		//"editorWarning.border": null,
		//"editorWidget.resizeBorder": null,
		//"input.border": null,
		//"inputValidation.errorForeground": null,
		//"inputValidation.infoForeground": null,
		//"inputValidation.warningForeground": null,
		//"list.activeSelectionIconForeground": null,
		//"list.filterMatchBorder": null,
		//"list.focusAndSelectionOutline": null,
		//"list.inactiveFocusBackground": null,
		//"list.inactiveFocusOutline": null,
		//"list.inactiveSelectionIconForeground": null,
		//"menu.border": null,
		//"menu.selectionBorder": null,
		//"menubar.selectionBorder": null,
		//"merge.border": null,
		//"minimap.background": null,
		//"notebook.cellHoverBackground": null,
		//"notebook.focusedCellBackground": null,
		//"notebook.inactiveSelectedCellBorder": null,
		//"notebook.outputContainerBackgroundColor": null,
		//"notebook.outputContainerBorderColor": null,
		//"notificationCenter.border": null,
		//"notificationCenterHeader.foreground": null,
		//"notificationToast.border": null,
		//"panelInput.border": null,
		//"panelSectionHeader.border": null,
		//"panelSectionHeader.foreground": null,
		//"peekViewEditor.matchHighlightBorder": null,
		//"quickInput.list.focusBackground": null,
		//"quickInputList.focusIconForeground": null,
		//"searchEditor.findMatchBorder": null,
		//"searchEditor.textInputBorder": null,
		//"settings.numberInputBorder": null,
		//"settings.textInputBorder": null,
		//"sideBar.border": null,
		//"sideBarSectionHeader.border": null,
		//"statusBar.border": null,
		//"statusBar.debuggingBorder": null,
		//"statusBar.noFolderBorder": null,
		//"statusBarItem.settingsProfilesBackground": null,
		//"statusBarItem.settingsProfilesForeground": null,
		//"tab.activeBorder": null,
		//"tab.activeBorderTop": null,
		//"tab.hoverBackground": null,
		//"tab.hoverBorder": null,
		//"tab.hoverForeground": null,
		//"tab.unfocusedActiveBorder": null,
		//"tab.unfocusedActiveBorderTop": null,
		//"tab.unfocusedHoverBackground": null,
		//"tab.unfocusedHoverBorder": null,
		//"tab.unfocusedHoverForeground": null,
		//"terminal.background": null,
		//"terminal.findMatchBorder": null,
		//"terminal.findMatchHighlightBorder": null,
		//"terminal.selectionForeground": null,
		//"terminal.tab.activeBorder": null,
		//"testing.message.info.lineBackground": null,
		//"titleBar.border": null,
		//"toolbar.hoverOutline": null,
		//"welcomePage.background": null,
		//"window.activeBorder": null,
		//"window.inactiveBorder": null
	},
	"tokenColors": [
		{
			"scope": [
				"strong"
			],
			"settings": {
				"fontStyle": "bold"
			}
		},
		{
			"scope": [
				"header"
			],
			"settings": {
				"foreground": "#BD93F9"
			}
		},
		{
			"scope": [
				"meta.diff",
				"meta.diff.header"
			],
			"settings": {
				"foreground": "#6272A4"
			}
		},
		{
			"scope": [
				"markup.inserted"
			],
			"settings": {
				"foreground": "#50FA7B"
			}
		},
		{
			"scope": [
				"markup.deleted"
			],
			"settings": {
				"foreground": "#FF5555"
			}
		},
		{
			"scope": [
				"markup.changed"
			],
			"settings": {
				"foreground": "#FFB86C"
			}
		},
		{
			"scope": [
				"invalid"
			],
			"settings": {
				"foreground": "#FF5555",
				"fontStyle": "underline italic"
			}
		},
		{
			"scope": [
				"invalid.deprecated"
			],
			"settings": {
				"foreground": "#F8F8F2",
				"fontStyle": "underline italic"
			}
		},
		{
			"scope": [
				"entity.name.filename"
			],
			"settings": {
				"foreground": "#F1FA8C"
			}
		},
		{
			"scope": [
				"markup.error"
			],
			"settings": {
				"foreground": "#FF5555"
			}
		},
		{
			"scope": [
				"markup.underline"
			],
			"settings": {
				"fontStyle": "underline"
			}
		},
		{
			"scope": [
				"markup.bold"
			],
			"settings": {
				"foreground": "#FFB86C",
				"fontStyle": "bold"
			}
		},
		{
			"scope": [
				"markup.heading"
			],
			"settings": {
				"foreground": "#BD93F9",
				"fontStyle": "bold"
			}
		},
		{
			"scope": [
				"markup.italic"
			],
			"settings": {
				"foreground": "#F1FA8C",
				"fontStyle": "italic"
			}
		},
		{
			"scope": [
				"beginning.punctuation.definition.list.markdown",
				"beginning.punctuation.definition.quote.markdown",
				"punctuation.definition.link.restructuredtext"
			],
			"settings": {
				"foreground": "#8BE9FD"
			}
		},
		{
			"scope": [
				"markup.inline.raw",
				"markup.raw.restructuredtext"
			],
			"settings": {
				"foreground": "#50FA7B"
			}
		},
		{
			"scope": [
				"markup.underline.link",
				"markup.underline.link.image"
			],
			"settings": {
				"foreground": "#8BE9FD"
			}
		},
		{
			"scope": [
				"meta.link.reference.def.restructuredtext",
				"punctuation.definition.directive.restructuredtext",
				"string.other.link.description",
				"string.other.link.title"
			],
			"settings": {
				"foreground": "#FF79C6"
			}
		},
		{
			"scope": [
				"entity.name.directive.restructuredtext",
				"markup.quote"
			],
			"settings": {
				"foreground": "#F1FA8C",
				"fontStyle": "italic"
			}
		},
		{
			"scope": [
				"meta.separator.markdown"
			],
			"settings": {
				"foreground": "#6272A4"
			}
		},
		{
			"scope": [
				"fenced_code.block.language",
				"markup.raw.inner.restructuredtext",
				"markup.fenced_code.block.markdown punctuation.definition.markdown"
			],
			"settings": {
				"foreground": "#50FA7B"
			}
		},
		{
			"scope": [
				"punctuation.definition.constant.restructuredtext"
			],
			"settings": {
				"foreground": "#BD93F9"
			}
		},
		{
			"scope": [
				"markup.heading.markdown punctuation.definition.string.begin",
				"markup.heading.markdown punctuation.definition.string.end"
			],
			"settings": {
				"foreground": "#BD93F9"
			}
		},
		{
			"scope": [
				"meta.paragraph.markdown punctuation.definition.string.begin",
				"meta.paragraph.markdown punctuation.definition.string.end"
			],
			"settings": {
				"foreground": "#F8F8F2"
			}
		},
		{
			"scope": [
				"markup.quote.markdown meta.paragraph.markdown punctuation.definition.string.begin",
				"markup.quote.markdown meta.paragraph.markdown punctuation.definition.string.end"
			],
			"settings": {
				"foreground": "#F1FA8C"
			}
		},
		{
			"scope": [
				"entity.name.type.class",
				"entity.name.class"
			],
			"settings": {
				"foreground": "#8BE9FD"
			}
		},
		{
			"scope": [
				"keyword.expressions-and-types.swift",
				"keyword.other.this",
				"variable.language",
				"variable.language punctuation.definition.variable.php",
				"variable.other.readwrite.instance.ruby",
				"variable.parameter.function.language.special"
			],
			"settings": {
				"foreground": "#BD93F9"
			}
		},
		{
			"scope": [
				"entity.other.inherited-class"
			],
			"settings": {
				"foreground": "#8BE9FD"
			}
		},
		{
			"scope": [
				"comment",
				"punctuation.definition.comment",
				"unused.comment",
				"wildcard.comment"
			],
			"settings": {
				"foreground": "#6272A4"
			}
		},
		{
			"scope": [
				"comment keyword.codetag.notation",
				"comment.block.documentation keyword",
				"comment.block.documentation storage.type.class"
			],
			"settings": {
				"foreground": "#FF79C6"
			}
		},
		{
			"scope": [
				"comment.block.documentation entity.name.type"
			],
			"settings": {
				"foreground": "#8BE9FD",
				"fontStyle": "italic"
			}
		},
		{
			"scope": [
				"comment.block.documentation entity.name.type punctuation.definition.bracket"
			],
			"settings": {
				"foreground": "#8BE9FD"
			}
		},
		{
			"scope": [
				"comment.block.documentation variable"
			],
			"settings": {
				"foreground": "#FFB86C",
				"fontStyle": "italic"
			}
		},
		{
			"scope": [
				"constant",
				"variable.other.constant"
			],
			"settings": {
				"foreground": "#BD93F9"
			}
		},
		{
			"scope": [
				"constant.character.escape",
				"constant.character.string.escape",
				"constant.regexp"
			],
			"settings": {
				"foreground": "#FF79C6"
			}
		},
		{
			"scope": [
				"entity.name.tag"
			],
			"settings": {
				"foreground": "#FF79C6"
			}
		},
		{
			"scope": [
				"entity.other.attribute-name.parent-selector"
			],
			"settings": {
				"foreground": "#FF79C6"
			}
		},
		{
			"scope": [
				"entity.other.attribute-name"
			],
			"settings": {
				"foreground": "#50FA7B"
			}
		},
		{
			"scope": [
				"entity.name.function",
				"meta.function-call.object",
				"meta.function-call.php",
				"meta.function-call.static",
				"meta.method-call.java meta.method",
				"meta.method.groovy",
				"support.function.any-method.lua",
				"keyword.operator.function.infix"
			],
			"settings": {
				"foreground": "#50FA7B"
			}
		},
		{
			"scope": [
				"entity.name.variable.parameter",
				"meta.at-rule.function variable",
				"meta.at-rule.mixin variable",
				"meta.function.arguments variable.other.php",
				"meta.selectionset.graphql meta.arguments.graphql variable.arguments.graphql",
				"variable.parameter"
			],
			"settings": {
				"foreground": "#FFB86C"
			}
		},
		{
			"scope": [
				"meta.decorator variable.other.readwrite",
				"meta.decorator variable.other.property"
			],
			"settings": {
				"foreground": "#50FA7B"
			}
		},
		{
			"scope": [
				"meta.decorator variable.other.object"
			],
			"settings": {
				"foreground": "#50FA7B"
			}
		},
		{
			"scope": [
				"keyword",
				"punctuation.definition.keyword"
			],
			"settings": {
				"foreground": "#FF79C6"
			}
		},
		{
			"scope": [
				"keyword.control.new",
				"keyword.operator.new"
			],
			"settings": {
				"fontStyle": "bold"
			}
		},
		{
			"scope": [
				"meta.selector"
			],
			"settings": {
				"foreground": "#FF79C6"
			}
		},
		{
			"scope": [
				"support"
			],
			"settings": {
				"foreground": "#8BE9FD",
				"fontStyle": "italic"
			}
		},
		{
			"scope": [
				"support.function.magic",
				"support.variable",
				"variable.other.predefined"
			],
			"settings": {
				"foreground": "#BD93F9"
			}
		},
		{
			"scope": [
				"support.function",
				"support.type.property-name"
			],
			"settings": {
			}
		},
		{
			"scope": [
				"constant.other.symbol.hashkey punctuation.definition.constant.ruby",
				"entity.other.attribute-name.placeholder punctuation",
				"entity.other.attribute-name.pseudo-class punctuation",
				"entity.other.attribute-name.pseudo-element punctuation",
				"meta.group.double.toml",
				"meta.group.toml",
				"meta.object-binding-pattern-variable punctuation.destructuring",
				"punctuation.colon.graphql",
				"punctuation.definition.block.scalar.folded.yaml",
				"punctuation.definition.block.scalar.literal.yaml",
				"punctuation.definition.block.sequence.item.yaml",
				"punctuation.definition.entity.other.inherited-class",
				"punctuation.function.swift",
				"punctuation.separator.dictionary.key-value",
				"punctuation.separator.hash",
				"punctuation.separator.inheritance",
				"punctuation.separator.key-value",
				"punctuation.separator.key-value.mapping.yaml",
				"punctuation.separator.namespace",
				"punctuation.separator.pointer-access",
				"punctuation.separator.slice",
				"string.unquoted.heredoc punctuation.definition.string",
				"support.other.chomping-indicator.yaml",
				"punctuation.separator.annotation"
			],
			"settings": {
				"foreground": "#FF79C6"
			}
		},
		{
			"scope": [
				"keyword.operator.other.powershell",
				"keyword.other.statement-separator.powershell",
				"meta.brace.round",
				"meta.function-call punctuation",
				"punctuation.definition.arguments.begin",
				"punctuation.definition.arguments.end",
				"punctuation.definition.entity.begin",
				"punctuation.definition.entity.end",
				"punctuation.definition.tag.cs",
				"punctuation.definition.type.begin",
				"punctuation.definition.type.end",
				"punctuation.section.scope.begin",
				"punctuation.section.scope.end",
				"punctuation.terminator.expression.php",
				"storage.type.generic.java",
				"string.template meta.brace",
				"string.template punctuation.accessor"
			],
			"settings": {
				"foreground": "#F8F8F2"
			}
		},
		{
			"scope": [
				"meta.string-contents.quoted.double punctuation.definition.variable",
				"punctuation.definition.interpolation.begin",
				"punctuation.definition.interpolation.end",
				"punctuation.definition.template-expression.begin",
				"punctuation.definition.template-expression.end",
				"punctuation.section.embedded.begin",
				"punctuation.section.embedded.coffee",
				"punctuation.section.embedded.end",
				"punctuation.section.embedded.end source.php",
				"punctuation.section.embedded.end source.ruby",
				"punctuation.definition.variable.makefile"
			],
			"settings": {
				"foreground": "#FF79C6"
			}
		},
		{
			"scope": [
				"entity.name.function.target.makefile",
				"entity.name.section.toml",
				"entity.name.tag.yaml",
				"variable.other.key.toml"
			],
			"settings": {
				"foreground": "#8BE9FD"
			}
		},
		{
			"scope": [
				"constant.other.date",
				"constant.other.timestamp"
			],
			"settings": {
				"foreground": "#FFB86C"
			}
		},
		{
			"scope": [
				"variable.other.alias.yaml"
			],
			"settings": {
				"foreground": "#50FA7B",
				"fontStyle": "italic underline"
			}
		},
		{
			"scope": [
				"storage",
				"meta.implementation storage.type.objc",
				"meta.interface-or-protocol storage.type.objc",
				"source.groovy storage.type.def"
			],
			"settings": {
				"foreground": "#FF79C6"
			}
		},
		{
			"scope": [
				"entity.name.type",
				"keyword.primitive-datatypes.swift",
				"keyword.type.cs",
				"meta.protocol-list.objc",
				"meta.return-type.objc",
				"source.go storage.type",
				"source.groovy storage.type",
				"source.java storage.type",
				"source.powershell entity.other.attribute-name",
				"storage.class.std.rust",
				"storage.type.attribute.swift",
				"storage.type.c",
				"storage.type.core.rust",
				"storage.type.cs",
				"storage.type.groovy",
				"storage.type.objc",
				"storage.type.php",
				"storage.type.haskell",
				"storage.type.ocaml"
			],
			"settings": {
				"foreground": "#8BE9FD"
			}
		},
		{
			"scope": [
				"entity.name.type.type-parameter",
				"meta.indexer.mappedtype.declaration entity.name.type",
				"meta.type.parameters entity.name.type"
			],
			"settings": {
				"foreground": "#FFB86C"
			}
		},
		{
			"scope": [
				"storage.modifier"
			],
			"settings": {
				"foreground": "#FF79C6"
			}
		},
		{
			"scope": [
				"string.regexp",
				"constant.other.character-class.set.regexp",
				"constant.character.escape.backslash.regexp"
			],
			"settings": {
				"foreground": "#F1FA8C"
			}
		},
		{
			"scope": [
				"punctuation.definition.group.capture.regexp"
			],
			"settings": {
				"foreground": "#FF79C6"
			}
		},
		{
			"scope": [
				"string.regexp punctuation.definition.string.begin",
				"string.regexp punctuation.definition.string.end"
			],
			"settings": {
				"foreground": "#FF5555"
			}
		},
		{
			"scope": [
				"punctuation.definition.character-class.regexp"
			],
			"settings": {
				"foreground": "#8BE9FD"
			}
		},
		{
			"scope": [
				"punctuation.definition.group.regexp"
			],
			"settings": {
				"foreground": "#FFB86C"
			}
		},
		{
			"scope": [
				"punctuation.definition.group.assertion.regexp",
				"keyword.operator.negation.regexp"
			],
			"settings": {
				"foreground": "#FF5555"
			}
		},
		{
			"scope": [
				"meta.assertion.look-ahead.regexp"
			],
			"settings": {
				"foreground": "#50FA7B"
			}
		},
		{
			"scope": [
				"string"
			],
			"settings": {
				"foreground": "#F1FA8C"
			}
		},
		{
			"scope": [
				"punctuation.definition.string.begin",
				"punctuation.definition.string.end"
			],
			"settings": {
				"foreground": "#E9F284"
			}
		},
		{
			"scope": [
				"punctuation.support.type.property-name.begin",
				"punctuation.support.type.property-name.end"
			],
			"settings": {
				"foreground": "#8BE9FE"
			}
		},
		{
			"scope": [
				"string.quoted.docstring.multi",
				"string.quoted.docstring.multi.python punctuation.definition.string.begin",
				"string.quoted.docstring.multi.python punctuation.definition.string.end",
				"string.quoted.docstring.multi.python constant.character.escape"
			],
			"settings": {
				"foreground": "#6272A4"
			}
		},
		{
			"scope": [
				"variable",
				"constant.other.key.perl",
				"support.variable.property",
				"variable.other.constant.js",
				"variable.other.constant.ts",
				"variable.other.constant.tsx"
			],
			"settings": {
				"foreground": "#F8F8F2"
			}
		},
		{
			"scope": [
				"meta.import variable.other.readwrite",
				"meta.variable.assignment.destructured.object.coffee variable"
			],
			"settings": {
				"foreground": "#FFB86C",
				"fontStyle": "italic"
			}
		},
		{
			"scope": [
				"meta.import variable.other.readwrite.alias",
				"meta.export variable.other.readwrite.alias",
				"meta.variable.assignment.destructured.object.coffee variable variable"
			],
			"settings": {
				"foreground": "#F8F8F2"
			}
		},
		{
			"scope": [
				"meta.selectionset.graphql variable"
			],
			"settings": {
				"foreground": "#F1FA8C"
			}
		},
		{
			"scope": [
				"meta.selectionset.graphql meta.arguments variable"
			],
			"settings": {
				"foreground": "#F8F8F2"
			}
		},
		{
			"scope": [
				"entity.name.fragment.graphql",
				"variable.fragment.graphql"
			],
			"settings": {
				"foreground": "#8BE9FD"
			}
		},
		{
			"scope": [
				"constant.other.symbol.hashkey.ruby",
				"keyword.operator.dereference.java",
				"keyword.operator.navigation.groovy",
				"meta.scope.for-loop.shell punctuation.definition.string.begin",
				"meta.scope.for-loop.shell punctuation.definition.string.end",
				"meta.scope.for-loop.shell string",
				"storage.modifier.import",
				"punctuation.section.embedded.begin.tsx",
				"punctuation.section.embedded.end.tsx",
				"punctuation.section.embedded.begin.jsx",
				"punctuation.section.embedded.end.jsx",
				"punctuation.separator.list.comma.css",
				"constant.language.empty-list.haskell"
			],
			"settings": {
				"foreground": "#F8F8F2"
			}
		},
		{
			"scope": [
				"source.shell variable.other"
			],
			"settings": {
				"foreground": "#BD93F9"
			}
		},
		{
			"scope": [
				"support.constant"
			],
			"settings": {
				"foreground": "#BD93F9"
			}
		},
		{
			"scope": [
				"meta.scope.prerequisites.makefile"
			],
			"settings": {
				"foreground": "#F1FA8C"
			}
		},
		{
			"scope": [
				"meta.attribute-selector.scss"
			],
			"settings": {
				"foreground": "#F1FA8C"
			}
		},
		{
			"scope": [
				"punctuation.definition.attribute-selector.end.bracket.square.scss",
				"punctuation.definition.attribute-selector.begin.bracket.square.scss"
			],
			"settings": {
				"foreground": "#F8F8F2"
			}
		},
		{
			"scope": [
				"meta.preprocessor.haskell"
			],
			"settings": {
				"foreground": "#6272A4"
			}
		},
		{
			"scope": [
				"log.error"
			],
			"settings": {
				"foreground": "#FF5555",
				"fontStyle": "bold"
			}
		},
		{
			"scope": [
				"log.warning"
			],
			"settings": {
				"foreground": "#F1FA8C",
				"fontStyle": "bold"
			}
		},
		{
			"scope": "token.info-token",
			"settings": {
				"foreground": "#6796E6"
			}
		},
		{
			"scope": "token.warn-token",
			"settings": {
				"foreground": "#CD9731"
			}
		},
		{
			"scope": "token.error-token",
			"settings": {
				"foreground": "#F44747"
			}
		},
		{
			"scope": "token.debug-token",
			"settings": {
				"foreground": "#B267E6"
			}
		}
	]
}
